odoo/addons/l10n_de_holidays/README.rst
odoo/addons/l10n_de_holidays/__init__.py
odoo/addons/l10n_de_holidays/__manifest__.py
odoo/addons/l10n_de_holidays/i18n/de.po
odoo/addons/l10n_de_holidays/i18n/l10n_de_holidays.pot
odoo/addons/l10n_de_holidays/static/description/icon.png
odoo/addons/l10n_de_holidays/tests/__init__.py
odoo/addons/l10n_de_holidays/tests/common.py
odoo/addons/l10n_de_holidays/tests/test_hr_holidays_public_generator.py
odoo/addons/l10n_de_holidays/wizards/__init__.py
odoo/addons/l10n_de_holidays/wizards/hr_holidays_public_generator.py
odoo/addons/l10n_de_holidays/wizards/hr_holidays_public_generator_de.py
odoo/addons/l10n_de_holidays/wizards/hr_holidays_public_generator_view.xml
odoo12_addon_l10n_de_holidays-12.0.1.0.0.99.dev10.dist-info/METADATA
odoo12_addon_l10n_de_holidays-12.0.1.0.0.99.dev10.dist-info/WHEEL
odoo12_addon_l10n_de_holidays-12.0.1.0.0.99.dev10.dist-info/top_level.txt
odoo12_addon_l10n_de_holidays-12.0.1.0.0.99.dev10.dist-info/RECORD
